myzippy/__init__.py
myzippy/length.py
myzippy-0.1.dist-info/METADATA
myzippy-0.1.dist-info/WHEEL
myzippy-0.1.dist-info/top_level.txt
myzippy-0.1.dist-info/RECORD
