Metadata-Version: 2.4
Name: myzippy
Version: 0.1
Summary: Highly scientific zipp measurement
Author: Dr. Zipp
Author-email: mailbot217@gmail.com
Classifier: Programming Language :: Python :: 3
Requires-Python: >=3.6
Dynamic: author
Dynamic: author-email
Dynamic: classifier
Dynamic: requires-python
Dynamic: summary
